istacky/BlendedImage.py
istacky/__init__.py
istacky-0.2.dist-info/METADATA
istacky-0.2.dist-info/WHEEL
istacky-0.2.dist-info/licenses/LICENSE
istacky-0.2.dist-info/RECORD
